[
  {
    "id": "event-chicago-proctors-2026-06-24",
    "name": "Chicago at Proctors",
    "title": "Chicago at Proctors",
    "category": "live music",
    "date": "2026-06-24T19:30:00+00:00",
    "time": "19:30",
    "venue": "Proctors Theatre",
    "location": "Proctors Theatre, Schenectady, NY",
    "coordinates": {
      "lat": 42.8142,
      "lng": -73.9396
    },
    "url": "https://www.timesunion.com/music/article/chicago-band-coming-upstate-new-york-tour-21858163.php",
    "source_url": "https://www.timesunion.com/music/article/chicago-band-coming-upstate-new-york-tour-21858163.php",
    "description": "Chicago performs at Proctors Theatre in Schenectady.",
    "duration_minutes": 150,
    "tags": [
      "concert",
      "classic rock",
      "schenectady"
    ],
    "neighborhood": "Schenectady"
  },
  {
    "id": "event-alive-at-five-afrobeats-2026-06-25",
    "name": "Alive at Five: Afrobeats Night",
    "title": "Alive at Five: Afrobeats Night",
    "category": "live music",
    "date": "2026-06-25T17:00:00+00:00",
    "time": "17:00",
    "venue": "Warehouse District",
    "location": "Warehouse District, Albany, NY",
    "coordinates": {
      "lat": 42.6642,
      "lng": -73.7451
    },
    "url": "https://www.timesunion.com/music/article/b-o-b-alive-at-five-albany-22309982.php",
    "source_url": "https://www.timesunion.com/music/article/b-o-b-alive-at-five-albany-22309982.php",
    "description": "Free Alive at Five concert featuring DJ TGIF, Soular Sounds and Afrellie.",
    "duration_minutes": 180,
    "tags": [
      "free",
      "concert",
      "albany",
      "afrobeats"
    ],
    "neighborhood": "Albany"
  },
  {
    "id": "event-fence-2026-reception-2026-06-26",
    "name": "Fence 2026 Opening Reception",
    "title": "Fence 2026 Opening Reception",
    "category": "art",
    "date": "2026-06-26T18:00:00+00:00",
    "time": "18:00",
    "venue": "The Arts Center of the Capital Region",
    "location": "The Arts Center of the Capital Region, Troy, NY",
    "coordinates": {
      "lat": 42.7284,
      "lng": -73.6918
    },
    "url": "https://www.timesunion.com/preview/article/events-albany-area-les-claypool-capital-pride-22297802.php",
    "source_url": "https://www.timesunion.com/preview/article/events-albany-area-les-claypool-capital-pride-22297802.php",
    "description": "Opening reception for Fence 2026, a juried show at The Arts Center.",
    "duration_minutes": 120,
    "tags": [
      "art",
      "opening",
      "troy"
    ],
    "neighborhood": "Troy"
  },
  {
    "id": "event-job-adirondack-theatre-festival-2026-06-26",
    "name": "Adirondack Theatre Festival: Job",
    "title": "Adirondack Theatre Festival: Job",
    "category": "art",
    "date": "2026-06-26T19:30:00+00:00",
    "time": "19:30",
    "venue": "Charles R. Wood Theater",
    "location": "Charles R. Wood Theater, Glens Falls, NY",
    "coordinates": {
      "lat": 43.3095,
      "lng": -73.644
    },
    "url": "https://www.timesunion.com/preview/article/events-albany-area-les-claypool-capital-pride-22297802.php",
    "source_url": "https://www.timesunion.com/preview/article/events-albany-area-les-claypool-capital-pride-22297802.php",
    "description": "Adirondack Theatre Festival production of Max Wolf Friedlich's psychological thriller Job.",
    "duration_minutes": 120,
    "tags": [
      "theater",
      "glens falls"
    ],
    "neighborhood": "Glens Falls"
  },
  {
    "id": "event-albany-institute-blanche-lazzell-2026-06-27",
    "name": "Blanche Lazzell: Becoming an American Modernist",
    "title": "Blanche Lazzell: Becoming an American Modernist",
    "category": "art",
    "date": "2026-06-27T10:00:00+00:00",
    "time": "10:00",
    "venue": "Albany Institute of History & Art",
    "location": "Albany Institute of History & Art, Albany, NY",
    "coordinates": {
      "lat": 42.6526,
      "lng": -73.7562
    },
    "url": "https://www.timesunion.com/preview/article/events-albany-area-les-claypool-capital-pride-22297802.php",
    "source_url": "https://www.timesunion.com/preview/article/events-albany-area-les-claypool-capital-pride-22297802.php",
    "description": "Albany Institute exhibition surveying Blanche Lazzell's modernist work.",
    "duration_minutes": 120,
    "tags": [
      "museum",
      "exhibition",
      "albany"
    ],
    "neighborhood": "Albany"
  },
  {
    "id": "event-fence-2026-exhibition-2026-06-27",
    "name": "Fence 2026 Exhibition",
    "title": "Fence 2026 Exhibition",
    "category": "art",
    "date": "2026-06-27T12:00:00+00:00",
    "time": "12:00",
    "venue": "The Arts Center of the Capital Region",
    "location": "The Arts Center of the Capital Region, Troy, NY",
    "coordinates": {
      "lat": 42.7284,
      "lng": -73.6918
    },
    "url": "https://www.timesunion.com/preview/article/events-albany-area-les-claypool-capital-pride-22297802.php",
    "source_url": "https://www.timesunion.com/preview/article/events-albany-area-les-claypool-capital-pride-22297802.php",
    "description": "Fence 2026 juried exhibition, on view through July 24.",
    "duration_minutes": 90,
    "tags": [
      "art",
      "gallery",
      "troy"
    ],
    "neighborhood": "Troy"
  },
  {
    "id": "event-nycb-innovators-icons-spac-2026-07-08",
    "name": "New York City Ballet: Innovators & Icons",
    "title": "New York City Ballet: Innovators & Icons",
    "category": "art",
    "date": "2026-07-08T19:30:00+00:00",
    "time": "19:30",
    "venue": "Saratoga Performing Arts Center",
    "location": "Saratoga Performing Arts Center, Saratoga Springs, NY",
    "coordinates": {
      "lat": 43.0554,
      "lng": -73.8059
    },
    "url": "https://www.timesunion.com/theater/article/new-york-city-ballet-brings-new-tiler-peck-work-21349620.php",
    "source_url": "https://www.timesunion.com/theater/article/new-york-city-ballet-brings-new-tiler-peck-work-21349620.php",
    "description": "NYCB program with a Tiler Peck world premiere, Balanchine and Robbins.",
    "duration_minutes": 150,
    "tags": [
      "ballet",
      "spac",
      "saratoga"
    ],
    "neighborhood": "Saratoga Springs"
  },
  {
    "id": "event-nycb-midsummer-spac-2026-07-09",
    "name": "New York City Ballet: A Midsummer Night's Dream",
    "title": "New York City Ballet: A Midsummer Night's Dream",
    "category": "art",
    "date": "2026-07-09T19:30:00+00:00",
    "time": "19:30",
    "venue": "Saratoga Performing Arts Center",
    "location": "Saratoga Performing Arts Center, Saratoga Springs, NY",
    "coordinates": {
      "lat": 43.0554,
      "lng": -73.8059
    },
    "url": "https://www.timesunion.com/theater/article/new-york-city-ballet-brings-new-tiler-peck-work-21349620.php",
    "source_url": "https://www.timesunion.com/theater/article/new-york-city-ballet-brings-new-tiler-peck-work-21349620.php",
    "description": "NYCB revives Balanchine's full-length A Midsummer Night's Dream at SPAC.",
    "duration_minutes": 150,
    "tags": [
      "ballet",
      "spac",
      "saratoga"
    ],
    "neighborhood": "Saratoga Springs"
  },
  {
    "id": "event-cms-dvorak-spac-2026-07-12",
    "name": "Chamber Music Society: Dvorak Quintet",
    "title": "Chamber Music Society: Dvorak Quintet",
    "category": "live music",
    "date": "2026-07-12T19:00:00+00:00",
    "time": "19:00",
    "venue": "Arthur Zankel Music Center",
    "location": "Arthur Zankel Music Center, Saratoga Springs, NY",
    "coordinates": {
      "lat": 43.0963,
      "lng": -73.786
    },
    "url": "https://www.timesunion.com/music/article/spac-announces-lincoln-center-summer-season-21199168.php",
    "source_url": "https://www.timesunion.com/music/article/spac-announces-lincoln-center-summer-season-21199168.php",
    "description": "Opening program of the Chamber Music Society of Lincoln Center's SPAC summer residency.",
    "duration_minutes": 120,
    "tags": [
      "classical",
      "saratoga",
      "skidmore"
    ],
    "neighborhood": "Saratoga Springs"
  },
  {
    "id": "event-train-barenaked-ladies-spac-2026-07-22",
    "name": "Train and Barenaked Ladies",
    "title": "Train and Barenaked Ladies",
    "category": "live music",
    "date": "2026-07-22T19:00:00+00:00",
    "time": "19:00",
    "venue": "Saratoga Performing Arts Center",
    "location": "Saratoga Performing Arts Center, Saratoga Springs, NY",
    "coordinates": {
      "lat": 43.0554,
      "lng": -73.8059
    },
    "url": "https://www.timesunion.com/music/article/train-barenaked-ladies-tour-saratoga-2026-21152353.php",
    "source_url": "https://www.timesunion.com/music/article/train-barenaked-ladies-tour-saratoga-2026-21152353.php",
    "description": "Train and Barenaked Ladies co-headline the Drops of Jupiter anniversary tour at SPAC.",
    "duration_minutes": 180,
    "tags": [
      "concert",
      "spac",
      "saratoga"
    ],
    "neighborhood": "Saratoga Springs"
  },
  {
    "id": "event-guns-n-roses-spac-2026-07-26",
    "name": "Guns N' Roses at SPAC",
    "title": "Guns N' Roses at SPAC",
    "category": "live music",
    "date": "2026-07-26T19:00:00+00:00",
    "time": "19:00",
    "venue": "Saratoga Performing Arts Center",
    "location": "Saratoga Performing Arts Center, Saratoga Springs, NY",
    "coordinates": {
      "lat": 43.0554,
      "lng": -73.8059
    },
    "url": "https://www.timesunion.com/music/article/guns-n-roses-bring-world-tour-spac-2026-21204762.php",
    "source_url": "https://www.timesunion.com/music/article/guns-n-roses-bring-world-tour-spac-2026-21204762.php",
    "description": "Guns N' Roses bring their world tour to Saratoga Performing Arts Center.",
    "duration_minutes": 180,
    "tags": [
      "concert",
      "rock",
      "spac",
      "saratoga"
    ],
    "neighborhood": "Saratoga Springs"
  },
  {
    "_meta": {
      "items_hash": "9b114544c6a4e869c2bd8584437c69632965b850f99ff842c40228942b39c07e",
      "items_changed": false,
      "item_count": 11
    }
  }
]